feature_analysis_tools/__init__.py
feature_analysis_tools/cka_analysis.py
feature_analysis_tools/feature_analysis.py
feature_analysis_tools/fisher_analysis.py
feature_analysis_tools/pca_shift_analysis.py
feature_analysis_tools/pca_sim_analysis.py
feature_analysis_tools/test.py
feature_analyzer-0.1.7.dist-info/METADATA
feature_analyzer-0.1.7.dist-info/WHEEL
feature_analyzer-0.1.7.dist-info/entry_points.txt
feature_analyzer-0.1.7.dist-info/top_level.txt
feature_analyzer-0.1.7.dist-info/RECORD
