Metadata-Version: 2.4
Name: feature_analyzer
Version: 0.1.7
Summary: feature analyzer for LLM
Author-email: XiaoyuXu <xuxiaoyu200@gmail.com>
License: MIT
Requires-Python: >=3.10
Requires-Dist: torch
Requires-Dist: transformers
Requires-Dist: datasets
Requires-Dist: matplotlib
Requires-Dist: scikit-learn
Requires-Dist: pandas
